{
  "ground": [
    {
      "img": "tiles/wald/base_1.png",
      "w": 1
    },
    {
      "img": "tiles/wald/base_2.png",
      "w": 1
    },
    {
      "img": "tiles/wald/base_3.png",
      "w": 1
    },
    {
      "img": "tiles/wald/base_4.png",
      "w": 1
    },
    {
      "img": "tiles/wald/base_5.png",
      "w": 1
    },
    {
      "img": "tiles/wald/base_6.png",
      "w": 1
    }
  ],
  "borders": [
    [
      {
        "img": "tiles/wald/b1.png",
        "w": 1
      },
      {
        "img": "tiles/wald/b1_2.png",
        "w": 1
      },
      {
        "img": "tiles/wald/b1_3.png",
        "w": 1
      }
    ],
    [
      {
        "img": "tiles/wald/b2.png",
        "w": 1
      },
      {
        "img": "tiles/wald/b2_2.png",
        "w": 1
      },
      {
        "img": "tiles/wald/b2_3.png",
        "w": 1
      }
    ],
    [
      {
        "img": "tiles/wald/b3.png",
        "w": 1
      },
      {
        "img": "tiles/wald/b3_2.png",
        "w": 1
      },
      {
        "img": "tiles/wald/b3_3.png",
        "w": 1
      }
    ],
    [
      {
        "img": "tiles/wald/b4.png",
        "w": 1
      },
      {
        "img": "tiles/wald/b4_2.png",
        "w": 1
      },
      {
        "img": "tiles/wald/b4_3.png",
        "w": 1
      }
    ],
    [
      {
        "img": "tiles/wald/b5.png",
        "w": 1
      },
      {
        "img": "tiles/wald/b5_2.png",
        "w": 1
      },
      {
        "img": "tiles/wald/b5_3.png",
        "w": 1
      }
    ],
    [
      {
        "img": "tiles/wald/b6.png",
        "w": 1
      },
      {
        "img": "tiles/wald/b6_2.png",
        "w": 1
      },
      {
        "img": "tiles/wald/b6_3.png",
        "w": 1
      }
    ],
    [
      {
        "img": "tiles/wald/b7.png",
        "w": 1
      },
      {
        "img": "tiles/wald/b7_2.png",
        "w": 1
      },
      {
        "img": "tiles/wald/b7_3.png",
        "w": 1
      }
    ],
    [
      {
        "img": "tiles/wald/b8.png",
        "w": 1
      },
      {
        "img": "tiles/wald/b8_2.png",
        "w": 1
      },
      {
        "img": "tiles/wald/b8_3.png",
        "w": 1
      }
    ],
    [
      {
        "img": "tiles/wald/b9.png",
        "w": 1
      },
      {
        "img": "tiles/wald/b9_2.png",
        "w": 1
      },
      {
        "img": "tiles/wald/b9_3.png",
        "w": 1
      }
    ],
    [
      {
        "img": "tiles/wald/b10.png",
        "w": 1
      },
      {
        "img": "tiles/wald/b10_2.png",
        "w": 1
      },
      {
        "img": "tiles/wald/b10_3.png",
        "w": 1
      }
    ],
    [
      {
        "img": "tiles/wald/b11.png",
        "w": 1
      },
      {
        "img": "tiles/wald/b11_2.png",
        "w": 1
      },
      {
        "img": "tiles/wald/b11_3.png",
        "w": 1
      }
    ],
    [
      {
        "img": "tiles/wald/b12.png",
        "w": 1
      },
      {
        "img": "tiles/wald/b12_2.png",
        "w": 1
      },
      {
        "img": "tiles/wald/b12_3.png",
        "w": 1
      }
    ],
    [
      {
        "img": "tiles/wald/b13.png",
        "w": 1
      },
      {
        "img": "tiles/wald/b13_2.png",
        "w": 1
      },
      {
        "img": "tiles/wald/b13_3.png",
        "w": 1
      }
    ],
    [
      {
        "img": "tiles/wald/b14.png",
        "w": 1
      },
      {
        "img": "tiles/wald/b14_2.png",
        "w": 1
      },
      {
        "img": "tiles/wald/b14_3.png",
        "w": 1
      }
    ],
    [
      {
        "img": "tiles/wald/b15.png",
        "w": 1
      },
      {
        "img": "tiles/wald/b15_2.png",
        "w": 1
      },
      {
        "img": "tiles/wald/b15_3.png",
        "w": 1
      }
    ]
  ],
  "corners": [
    [
      {
        "img": "tiles/wald/c1.png",
        "w": 1
      },
      {
        "img": "tiles/wald/c1_2.png",
        "w": 1
      },
      {
        "img": "tiles/wald/c1_3.png",
        "w": 1
      }
    ], [
      {
        "img": "tiles/wald/c2.png",
        "w": 1
      },
      {
        "img": "tiles/wald/c2_2.png",
        "w": 1
      },
      {
        "img": "tiles/wald/c2_3.png",
        "w": 1
      }
    ], [
      {
        "img": "tiles/wald/c3.png",
        "w": 1
      },
      {
        "img": "tiles/wald/c3_2.png",
        "w": 1
      },
      {
        "img": "tiles/wald/c3_3.png",
        "w": 1
      }
    ], [
      {
        "img": "tiles/wald/c4.png",
        "w": 1
      },
      {
        "img": "tiles/wald/c4_2.png",
        "w": 1
      },
      {
        "img": "tiles/wald/c4_3.png",
        "w": 1
      }
    ], [
      {
        "img": "tiles/wald/c5.png",
        "w": 1
      },
      {
        "img": "tiles/wald/c5_2.png",
        "w": 1
      },
      {
        "img": "tiles/wald/c5_3.png",
        "w": 1
      }
    ], [
      {
        "img": "tiles/wald/c6.png",
        "w": 1
      },
      {
        "img": "tiles/wald/c6_2.png",
        "w": 1
      },
      {
        "img": "tiles/wald/c6_3.png",
        "w": 1
      }
    ], [
      {
        "img": "tiles/wald/c7.png",
        "w": 1
      },
      {
        "img": "tiles/wald/c7_2.png",
        "w": 1
      },
      {
        "img": "tiles/wald/c7_3.png",
        "w": 1
      }
    ], [
      {
        "img": "tiles/wald/c8.png",
        "w": 1
      },
      {
        "img": "tiles/wald/c8_2.png",
        "w": 1
      },
      {
        "img": "tiles/wald/c8_3.png",
        "w": 1
      }
    ], [
      {
        "img": "tiles/wald/c9.png",
        "w": 1
      },
      {
        "img": "tiles/wald/c9_2.png",
        "w": 1
      },
      {
        "img": "tiles/wald/c9_3.png",
        "w": 1
      }
    ], [
      {
        "img": "tiles/wald/c10.png",
        "w": 1
      },
      {
        "img": "tiles/wald/c10_2.png",
        "w": 1
      },
      {
        "img": "tiles/wald/c10_3.png",
        "w": 1
      }
    ], [
      {
        "img": "tiles/wald/c11.png",
        "w": 1
      },
      {
        "img": "tiles/wald/c11_2.png",
        "w": 1
      },
      {
        "img": "tiles/wald/c11_3.png",
        "w": 1
      }
    ], [
      {
        "img": "tiles/wald/c12.png",
        "w": 1
      },
      {
        "img": "tiles/wald/c12_2.png",
        "w": 1
      },
      {
        "img": "tiles/wald/c12_3.png",
        "w": 1
      }
    ], [
      {
        "img": "tiles/wald/c13.png",
        "w": 1
      },
      {
        "img": "tiles/wald/c13_2.png",
        "w": 1
      },
      {
        "img": "tiles/wald/c13_3.png",
        "w": 1
      }
    ], [
      {
        "img": "tiles/wald/c14.png",
        "w": 1
      },
      {
        "img": "tiles/wald/c14_2.png",
        "w": 1
      },
      {
        "img": "tiles/wald/c14_3.png",
        "w": 1
      }
    ], [
      {
        "img": "tiles/wald/c15.png",
        "w": 1
      },
      {
        "img": "tiles/wald/c15_2.png",
        "w": 1
      },
      {
        "img": "tiles/wald/c15_3.png",
        "w": 1
      }
    ]
  ]
}